pySulfiLoggerAPI/__init__.py
pySulfiLoggerAPI/sensor.py
pySulfiLoggerAPI/webData.py
pySulfiLoggerAPI-0.0.6.dist-info/METADATA
pySulfiLoggerAPI-0.0.6.dist-info/WHEEL
pySulfiLoggerAPI-0.0.6.dist-info/top_level.txt
pySulfiLoggerAPI-0.0.6.dist-info/RECORD
