Metadata-Version: 2.1
Name: pySulfiLoggerAPI
Version: 0.0.6
Summary: Driver module for the SulfiLogger sensor
Home-page: https://sulfilogger.com
Author: Unisense
Author-email: sulfilogger@unisense.com
License: UNKNOWN
Platform: UNKNOWN
Classifier: Programming Language :: Python :: 3.7
Classifier: Programming Language :: Python :: Implementation :: PyPy
Requires-Dist: pyserial
Requires-Dist: requests
Requires-Dist: pandas
Requires-Dist: pytz
